respo/__init__.py
respo/cli.py
respo/client.py
respo/core.py
respo/exceptions.py
respo/fields/__init__.py
respo/fields/django.py
respo/fields/sqlalchemy.py
respo/settings.py
respo/version.py
respo-1.0.0.dist-info/entry_points.txt
respo-1.0.0.dist-info/LICENSE
respo-1.0.0.dist-info/WHEEL
respo-1.0.0.dist-info/METADATA
respo-1.0.0.dist-info/RECORD
