Metadata-Version: 2.1
Name: respo
Version: 1.0.0
Summary: File based RBAC in Python made easy.
Home-page: https://github.com/rafsaf/respo
License: MIT
Author: rafsaf
Author-email: rafal.safin@rafsaf.pl
Requires-Python: >=3.8,<4.0
Classifier: Development Status :: 4 - Beta
Classifier: Intended Audience :: Developers
Classifier: License :: OSI Approved :: MIT License
Classifier: Programming Language :: Python :: 3
Classifier: Programming Language :: Python :: 3 :: Only
Classifier: Programming Language :: Python :: 3.10
Classifier: Programming Language :: Python :: 3.7
Classifier: Programming Language :: Python :: 3.8
Classifier: Programming Language :: Python :: 3.9
Classifier: Topic :: Internet :: WWW/HTTP :: HTTP Servers
Classifier: Typing :: Typed
Provides-Extra: all
Provides-Extra: cli
Provides-Extra: django
Provides-Extra: sqlalchemy
Requires-Dist: PyYAML (>=5.0); extra == "all" or extra == "cli"
Requires-Dist: SQLAlchemy (>=1.4.3); extra == "all" or extra == "sqlalchemy"
Requires-Dist: click (>=6.0.0); extra == "all" or extra == "cli"
Requires-Dist: django (>=3.1); extra == "all" or extra == "django"
Requires-Dist: pydantic (>=1.7.0)
Project-URL: Documentation, https://respo.rafsaf.pl
Project-URL: Repository, https://github.com/rafsaf/respo
